rapidfuzz.libs/libstdc++-29c3693a.so.6.0.32
rapidfuzz.libs/libgcc_s-18b5a48e.so.1
rapidfuzz-3.9.7.dist-info/RECORD
rapidfuzz-3.9.7.dist-info/entry_points.txt
rapidfuzz-3.9.7.dist-info/WHEEL
rapidfuzz-3.9.7.dist-info/LICENSE
rapidfuzz-3.9.7.dist-info/top_level.txt
rapidfuzz-3.9.7.dist-info/METADATA
rapidfuzz/process.pyi
rapidfuzz/_utils.py
rapidfuzz/process_py.py
rapidfuzz/process_cpp_impl.cpython-38-powerpc64le-linux-gnu.so
rapidfuzz/__init__.pyi
rapidfuzz/process_cpp.py
rapidfuzz/py.typed
rapidfuzz/utils_py.py
rapidfuzz/utils.py
rapidfuzz/utils_cpp.cpython-38-powerpc64le-linux-gnu.so
rapidfuzz/__init__.pxd
rapidfuzz/fuzz_cpp.cpython-38-powerpc64le-linux-gnu.so
rapidfuzz/fuzz_py.py
rapidfuzz/__init__.py
rapidfuzz/fuzz.pyi
rapidfuzz/_feature_detector.py
rapidfuzz/process.py
rapidfuzz/utils.pyi
rapidfuzz/_common_py.py
rapidfuzz/rapidfuzz.h
rapidfuzz/fuzz.py
rapidfuzz/__pyinstaller/hook-rapidfuzz.py
rapidfuzz/__pyinstaller/test_rapidfuzz_packaging.py
rapidfuzz/__pyinstaller/__init__.py
rapidfuzz/distance/Postfix.pyi
rapidfuzz/distance/metrics_py.py
rapidfuzz/distance/Prefix.py
rapidfuzz/distance/__init__.pyi
rapidfuzz/distance/OSA.pyi
rapidfuzz/distance/Indel.py
rapidfuzz/distance/Jaro_py.py
rapidfuzz/distance/_initialize_cpp.cpython-38-powerpc64le-linux-gnu.so
rapidfuzz/distance/Levenshtein.py
rapidfuzz/distance/Postfix.py
rapidfuzz/distance/Prefix_py.py
rapidfuzz/distance/DamerauLevenshtein.pyi
rapidfuzz/distance/JaroWinkler.py
rapidfuzz/distance/OSA_py.py
rapidfuzz/distance/Hamming_py.py
rapidfuzz/distance/metrics_cpp.cpython-38-powerpc64le-linux-gnu.so
rapidfuzz/distance/Indel_py.py
rapidfuzz/distance/__init__.py
rapidfuzz/distance/OSA.py
rapidfuzz/distance/DamerauLevenshtein_py.py
rapidfuzz/distance/LCSseq.pyi
rapidfuzz/distance/Indel.pyi
rapidfuzz/distance/Jaro.pyi
rapidfuzz/distance/DamerauLevenshtein.py
rapidfuzz/distance/_initialize.pyi
rapidfuzz/distance/_initialize_py.py
rapidfuzz/distance/Hamming.pyi
rapidfuzz/distance/Levenshtein.pyi
rapidfuzz/distance/LCSseq.py
rapidfuzz/distance/Prefix.pyi
rapidfuzz/distance/Hamming.py
rapidfuzz/distance/Postfix_py.py
rapidfuzz/distance/Levenshtein_py.py
