Metadata-Version: 2.1
Name: rapidfuzz
Version: 3.9.7
Summary: rapid fuzzy string matching
Home-page: https://github.com/rapidfuzz/RapidFuzz
Author: Max Bachmann
Author-email: pypi@maxbachmann.de
License: MIT
Classifier: Programming Language :: Python :: 3
Classifier: Programming Language :: Python :: 3.8
Classifier: Programming Language :: Python :: 3.9
Classifier: Programming Language :: Python :: 3.10
Classifier: Programming Language :: Python :: 3.11
Classifier: Programming Language :: Python :: 3.12
Classifier: License :: OSI Approved :: MIT License
Requires-Python: >=3.8
License-File: LICENSE
Provides-Extra: full
Requires-Dist: numpy; extra == "full"
